odoo/addons/website_sale_comparison_hide_price/README.rst
odoo/addons/website_sale_comparison_hide_price/__init__.py
odoo/addons/website_sale_comparison_hide_price/__manifest__.py
odoo/addons/website_sale_comparison_hide_price/i18n/website_sale_comparison_hide_price.pot
odoo/addons/website_sale_comparison_hide_price/readme/CONTRIBUTORS.rst
odoo/addons/website_sale_comparison_hide_price/readme/DESCRIPTION.rst
odoo/addons/website_sale_comparison_hide_price/static/description/icon.png
odoo/addons/website_sale_comparison_hide_price/static/description/index.html
odoo/addons/website_sale_comparison_hide_price/views/website_sale_template.xml
odoo13_addon_website_sale_comparison_hide_price-13.0.2.0.0.dist-info/METADATA
odoo13_addon_website_sale_comparison_hide_price-13.0.2.0.0.dist-info/WHEEL
odoo13_addon_website_sale_comparison_hide_price-13.0.2.0.0.dist-info/top_level.txt
odoo13_addon_website_sale_comparison_hide_price-13.0.2.0.0.dist-info/RECORD
